{
  "name": "SippaMenu",
  "version": "0.0.1",
  "author": "Ionic F{\n  \"name\": \"SippaMenu\",\n  \"version\": \"0.0.1\",\n  \"author\": \"Ionic Framework\",\n  \"homepage\": \"https://ionicframework.com/\",\n  \"scripts\": {\n    \"ng\": \"ng\",\n    \"start\": \"ng serve\",\n    \"build\": \"ng build\",\n    \"watch\": \"ng build --watch --configuration development\",\n    \"test\": \"ng test\",\n    \"lint\": \"ng lint\"\n  },\n  \"private\": true,\n  \"dependencies\": {\n    \"@angular/animations\": \"^20.0.0\",\n    \"@angular/common\": \"^20.0.0\",\n    \"@angular/compiler\": \"^20.0.0\",\n    \"@angular/core\": \"^20.0.0\",\n    \"@angular/forms\": \"^20.0.0\",\n    \"@angular/platform-browser\": \"^20.0.0\",\n    \"@angular/platform-browser-dynamic\": \"^20.0.0\",\n    \"@angular/router\": \"^20.0.0\",\n    \"@capacitor/android\": \"^7.4.4\",\n    \"@capacitor/app\": \"7.1.0\",\n    \"@capacitor/assets\": \"^3.0.5\",\n    \"@capacitor/core\": \"7.4.4\",\n    \"@capacitor/haptics\": \"7.0.2\",\n    \"@capacitor/keyboard\": \"7.0.3\",\n    \"@capacitor/network\": \"^7.0.2\",\n    \"@capacitor/preferences\": \"^7.0.3\",\n    \"@capacitor/status-bar\": \"7.0.3\",\n    \"@ionic/angular\": \"^8.0.0\",\n    \"@supabase/supabase-js\": \"^2.86.0\",\n    \"ionicons\": \"^7.0.0\",\n    \"jeep-sqlite\": \"^2.8.0\",\n    \"rxjs\": \"~7.8.0\",\n    \"tslib\": \"^2.3.0\",\n    \"zone.js\": \"~0.15.0\"\n  },\n  \"devDependencies\": {\n    \"@angular-devkit/build-angular\": \"^20.0.0\",\n    \"@angular-eslint/builder\": \"^20.0.0\",\n    \"@angular-eslint/eslint-plugin\": \"^20.0.0\",\n    \"@angular-eslint/eslint-plugin-template\": \"^20.0.0\",\n    \"@angular-eslint/schematics\": \"^20.0.0\",\n    \"@angular-eslint/template-parser\": \"^20.0.0\",\n    \"@angular/cli\": \"^20.0.0\",\n    \"@angular/compiler-cli\": \"^20.0.0\",\n    \"@angular/language-service\": \"^20.0.0\",\n    \"@capacitor/cli\": \"7.4.4\",\n    \"@ionic/angular-toolkit\": \"^12.0.0\",\n    \"@types/jasmine\": \"~5.1.0\",\n    \"@typescript-eslint/eslint-plugin\": \"^8.18.0\",\n    \"@typescript-eslint/parser\": \"^8.18.0\",\n    \"eslint\": \"^9.16.0\",\n    \"eslint-plugin-import\": \"^2.29.1\",\n    \"eslint-plugin-jsdoc\": \"^48.2.1\",\n    \"eslint-plugin-prefer-arrow\": \"1.2.2\",\n    \"jasmine-core\": \"~5.1.0\",\n    \"jasmine-spec-reporter\": \"~5.0.0\",\n    \"karma\": \"~6.4.0\",\n    \"karma-chrome-launcher\": \"~3.2.0\",\n    \"karma-coverage\": \"~2.2.0\",\n    \"karma-jasmine\": \"~5.1.0\",\n    \"karma-jasmine-html-reporter\": \"~2.1.0\",\n    \"typescript\": \"~5.9.0\"\n  },\n  \"description\": \"An Ionic project\"\n}\nramework",
  "homepage": "https://ionicframework.com/",
  "scripts": {
    "ng": "ng",
    "start": "ng serve",
    "build": "ng build",
    "watch": "ng build --watch --configuration development",
    "test": "ng test",
    "lint": "ng lint"
  },
  "private": true,
  "dependencies": {
    "@angular/animations": "^20.0.0",
    "@angular/common": "^20.0.0",
    "@angular/compiler": "^20.0.0",
    "@angular/core": "^20.0.0",
    "@angular/forms": "^20.0.0",
    "@angular/platform-browser": "^20.0.0",
    "@angular/platform-browser-dynamic": "^20.0.0",
    "@angular/router": "^20.0.0",
    "@capacitor-community/sqlite": "^7.0.2",
    "@capacitor/android": "^7.4.4",
    "@capacitor/app": "7.1.0",
    "@capacitor/assets": "^3.0.5",
    "@capacitor/core": "7.4.4",
    "@capacitor/haptics": "7.0.2",
    "@capacitor/keyboard": "7.0.3",
    "@capacitor/network": "^7.0.2",
    "@capacitor/preferences": "^7.0.3",
    "@capacitor/status-bar": "7.0.3",
    "@ionic/angular": "^8.0.0",
    "@supabase/supabase-js": "^2.86.0",
    "ionicons": "^7.0.0",
    "jeep-sqlite": "^2.8.0",
    "rxjs": "~7.8.0",
    "tslib": "^2.3.0",
    "zone.js": "~0.15.0"
  },
  "devDependencies": {
    "@angular-devkit/build-angular": "^20.0.0",
    "@angular-eslint/builder": "^20.0.0",
    "@angular-eslint/eslint-plugin": "^20.0.0",
    "@angular-eslint/eslint-plugin-template": "^20.0.0",
    "@angular-eslint/schematics": "^20.0.0",
    "@angular-eslint/template-parser": "^20.0.0",
    "@angular/cli": "^20.0.0",
    "@angular/compiler-cli": "^20.0.0",
    "@angular/language-service": "^20.0.0",
    "@capacitor/cli": "7.4.4",
    "@ionic/angular-toolkit": "^12.0.0",
    "@types/jasmine": "~5.1.0",
    "@typescript-eslint/eslint-plugin": "^8.18.0",
    "@typescript-eslint/parser": "^8.18.0",
    "eslint": "^9.16.0",
    "eslint-plugin-import": "^2.29.1",
    "eslint-plugin-jsdoc": "^48.2.1",
    "eslint-plugin-prefer-arrow": "1.2.2",
    "jasmine-core": "~5.1.0",
    "jasmine-spec-reporter": "~5.0.0",
    "karma": "~6.4.0",
    "karma-chrome-launcher": "~3.2.0",
    "karma-coverage": "~2.2.0",
    "karma-jasmine": "~5.1.0",
    "karma-jasmine-html-reporter": "~2.1.0",
    "typescript": "~5.9.0"
  },
  "description": "An Ionic project"
}
